{"17": {"2": {"dst_sw_id": "13", "collisions": 0, "duration_nsec": 413000000, "duration_sec": 110, "rx_bytes": 6846040, "rx_crc_err": 0, "rx_dropped": 0, "rx_errors": 0, "rx_frame_err": 0, "rx_over_err": 0, "rx_packets": 466, "tx_bytes": 32339, "tx_dropped": 0, "tx_errors": 0, "tx_packets": 459}, "3": {"dst_sw_id": "19", "collisions": 0, "duration_nsec": 413000000, "duration_sec": 110, "rx_bytes": 9189547, "rx_crc_err": 0, "rx_dropped": 0, "rx_errors": 0, "rx_frame_err": 0, "rx_over_err": 0, "rx_packets": 429, "tx_bytes": 30689, "tx_dropped": 0, "tx_errors": 0, "tx_packets": 430}, "4": {"dst_sw_id": "20", "collisions": 0, "duration_nsec": 415000000, "duration_sec": 110, "rx_bytes": 13825, "rx_crc_err": 0, "rx_dropped": 0, "rx_errors": 0, "rx_frame_err": 0, "rx_over_err": 0, "rx_packets": 179, "tx_bytes": 1977296, "tx_dropped": 0, "tx_errors": 0, "tx_packets": 182}}}